{
  "flights": [
    {
      "id": "1",
      "flightNumber": "ABC123",
      "scheduleTime": "2024-07-24 10:00",
      "seatLayout": [
        ["1A", "1B", "1C", "", "1D", "1E", "1F"],
        ["2A", "2B", "2C", "", "2D", "2E", "2F"],
        ["3A", "3B", "3C", "", "3D", "3E", "3F"],
        ["4A", "4B", "4C", "", "4D", "4E", "4F"],
        ["5A", "5B", "5C", "", "5D", "5E", "5F"],
        ["6A", "6B", "6C", "", "6D", "6E", "6F"],
        ["7A", "7B", "7C", "", "7D", "7E", "7F"],
        ["8A", "8B", "8C", "", "8D", "8E", "8F"],
        ["9A", "9B", "9C", "", "9D", "9E", "9F"],
        ["10A", "10B", "10C", "", "10D", "10E", "10F"]
      ],
      "ancillaryServices": [
        "Meals",
        "Baggage",
        "Seating",
        "Lounge Access",
        "Priority Boarding",
        "Car Rentals",
        "Hotel Booking",
        "Travel Insurance"
      ],
      "meals": [
        "AVML: Asian Vegetarian Meal",
        "BBML: Baby Meal",
        "CAKE: Birthday Cake",
        "BLML: Bland Meal",
        "CHML: Children Meal",
        "FPML: Fruit Platter Meal",
        "HFML: High Fibre Meal",
        "JPML: Japanese Meal",
        "JNML: Junior Meal",
        "SFML: Seafood Meal",
        "VGML or VVML: Vegetarian Vegan Meal"
      ],
      "shoppingItems": [
        "Watches",
        "Sun Glasses",
        "Travel Essentials",
        "Jewellery",
        "Cosmetics",
        "Bags",
        "Books",
        "Electronics"
      ],
      "passengers": [
        {
          "id": 1,
          "name": "Dani",
          "ancillaryServices": ["Seating"],
          "mealPreference": ["BBML: Baby Meal"],
          "inFlightShopRequests": ["Watches"],
          "seatNumber": "1A",
          "isCheckedIn": false,
          "requiresWheelchair": false,
          "hasInfant": false,
          "passport": "No",
          "address": "INDIA",
          "dob": "24-08-2000"
        },
        {
          "id": 2,
          "name": "Jane Smith",
          "ancillaryServices": [
            "Priority Boarding",
            "In-flight Meal",
            "Hotel Booking"
          ],
          "mealPreference": ["BBML: Baby Meal"],
          "inFlightShopRequests": ["Bags", "Shoes"],
          "seatNumber": "B",
          "isCheckedIn": false,
          "requiresWheelchair": true,
          "hasInfant": false,
          "passport": "Available",
          "address": "America",
          "dob": "24-08-1999"
        },
        {
          "id": 3,
          "name": "Jack Ryan",
          "ancillaryServices": ["Priority Boarding"],
          "mealPreference": ["BBML: Baby Meal"],
          "inFlightShopRequests": ["Chockolates", "Wine"],
          "seatNumber": "C",
          "isCheckedIn": false,
          "requiresWheelchair": true,
          "hasInfant": true,
          "passport": "Available",
          "address": "",
          "dob": "24-08-2000"
        },
        {
          "id": 4,
          "name": "Dane Smith",
          "ancillaryServices": ["Priority Boarding", "In-flight Meal"],
          "mealPreference": ["BBML: Baby Meal"],
          "inFlightShopRequests": ["Bag", "Shoes"],
          "seatNumber": "D",
          "isCheckedIn": true,
          "requiresWheelchair": true,
          "hasInfant": false,
          "passport": "Available",
          "address": "India",
          "dob": ""
        },
        {
          "id": 1727202373816,
          "name": "Akhila Queen",
          "passport": "122",
          "address": "TNK",
          "dob": "",
          "ancillaryServices": ["Na"],
          "mealPreference": ["BBML: Baby Meal"],
          "inFlightShopRequests": ["Jewellery", "Watches"],
          "seatNumber": "12",
          "isCheckedIn": true,
          "requiresWheelchair": false,
          "hasInfant": false
        }
      ]
    },
    {
      "id": "2",
      "flightNumber": "ABC1234",
      "scheduleTime": "2024-07-24 11:00",
      "seatLayout": [
        ["1A", "1B", "1C", "", "1D", "1E", "1F"],
        ["2A", "2B", "2C", "", "2D", "2E", "2F"],
        ["3A", "3B", "3C", "", "3D", "3E", "3F"],
        ["4A", "4B", "4C", "", "4D", "4E", "4F"],
        ["5A", "5B", "5C", "", "5D", "5E", "5F"],
        ["6A", "6B", "6C", "", "6D", "6E", "6F"],
        ["7A", "7B", "7C", "", "7D", "7E", "7F"],
        ["8A", "8B", "8C", "", "8D", "8E", "8F"],
        ["9A", "9B", "9C", "", "9D", "9E", "9F"],
        ["10A", "10B", "10C", "", "10D", "10E", "10F"]
      ],
      "ancillaryServices": [
        "Meals",
        "Baggage",
        "Seating",
        "Lounge Access",
        "Priority Boarding",
        "Car Rentals",
        "Hotel Booking",
        "Travel Insurance"
      ],
      "meals": [
        "AVML: Asian Vegetarian Meal",
        "BBML: Baby Meal",
        "CAKE: Birthday Cake",
        "BLML: Bland Meal",
        "CHML: Children Meal",
        "FPML: Fruit Platter Meal",
        "HFML: High Fibre Meal",
        "JPML: Japanese Meal",
        "JNML: Junior Meal",
        "SFML: Seafood Meal",
        "VGML or VVML: Vegetarian Vegan Meal"
      ],
      "shoppingItems": [
        "Watches",
        "Sun Glasses",
        "Travel Essentials",
        "Jewellery",
        "Cosmetics",
        "Bags",
        "Books",
        "Electronics"
      ],
      "passengers": [
        {
          "id": 1,
          "name": "John",
          "ancillaryServices": ["Extra Legroom", "In-flight Meal"],
          "mealPreference": ["BBML: Baby Meal"],
          "inFlightShopRequests": ["Chockolates", "Wine"],
          "seatNumber": "1A",
          "isCheckedIn": true,
          "requiresWheelchair": false,
          "hasInfant": false,
          "passport": "",
          "address": "India",
          "dob": ""
        },
        {
          "id": 2,
          "name": "Smith",
          "ancillaryServices": ["Priority Boarding"],
          "mealPreference": ["BBML: Baby Meal"],
          "inFlightShopRequests": ["Bags", "Shoes"],
          "seatNumber": "1B",
          "isCheckedIn": false,
          "requiresWheelchair": true,
          "hasInfant": false,
          "passport": "Available",
          "address": "",
          "dob": ""
        }
      ]
    }
  ]
}
